poetry_packaging_demo/__init__.py
poetry_packaging_demo/util.py
poetry_packaging_demo-1.3.4.dist-info/LICENSE
poetry_packaging_demo-1.3.4.dist-info/METADATA
poetry_packaging_demo-1.3.4.dist-info/WHEEL
poetry_packaging_demo-1.3.4.dist-info/RECORD
